yaycl_crypt/__init__.py
yaycl_crypt-0.4.0.dist-info/DESCRIPTION.rst
yaycl_crypt-0.4.0.dist-info/METADATA
yaycl_crypt-0.4.0.dist-info/RECORD
yaycl_crypt-0.4.0.dist-info/WHEEL
yaycl_crypt-0.4.0.dist-info/entry_points.txt
yaycl_crypt-0.4.0.dist-info/metadata.json
yaycl_crypt-0.4.0.dist-info/pbr.json
yaycl_crypt-0.4.0.dist-info/top_level.txt
