Metadata-Version: 2.0
Name: yaycl-crypt
Version: 0.4.0
Summary: YAML Config Autoloader Encryption Support
Home-page: https://github.com/seandst/yaycl-crypt
Author: Sean myers
Author-email: semyers@redhat.com
License: MIT
Platform: UNKNOWN
Classifier: Development Status :: 4 - Beta
Classifier: Environment :: Console
Classifier: Intended Audience :: Developers
Classifier: Intended Audience :: Information Technology
Classifier: License :: OSI Approved :: MIT License
Classifier: Operating System :: OS Independent
Classifier: Programming Language :: Python
Requires-Dist: yaycl
Requires-Dist: cryptography
Requires-Dist: wheel
